threemystic_cloud_cmdb/__main__.py
threemystic_cloud_cmdb/__version__.py
threemystic_cloud_cmdb/cloud_cmdb_client.py
threemystic_cloud_cmdb/cli/__init__.py
threemystic_cloud_cmdb/cli/actions/base_class/base.py
threemystic_cloud_cmdb/cli/actions/config/__init__.py
threemystic_cloud_cmdb/cloud_providers/aws/__init__.py
threemystic_cloud_cmdb/cloud_providers/aws/base_class/base.py
threemystic_cloud_cmdb/cloud_providers/aws/client/__init__.py
threemystic_cloud_cmdb/cloud_providers/aws/config/step_1.py
threemystic_cloud_cmdb/cloud_providers/aws/config/base_class/base.py
threemystic_cloud_cmdb/cloud_providers/azure/__init__.py
threemystic_cloud_cmdb/cloud_providers/azure/base_class/base.py
threemystic_cloud_cmdb/cloud_providers/azure/client/__init__.py
threemystic_cloud_cmdb/cloud_providers/azure/client/actions/budget.py
threemystic_cloud_cmdb/cloud_providers/azure/client/actions/cloudstorage.py
threemystic_cloud_cmdb/cloud_providers/azure/client/actions/storage.py
threemystic_cloud_cmdb/cloud_providers/azure/client/actions/vm.py
threemystic_cloud_cmdb/cloud_providers/azure/client/actions/base_class/base.py
threemystic_cloud_cmdb/cloud_providers/azure/config/step_1.py
threemystic_cloud_cmdb/cloud_providers/azure/config/base_class/base.py
threemystic_cloud_cmdb/cloud_providers/base_class/base.py
threemystic_cloud_cmdb/cloud_providers/base_class/base_client.py
threemystic_cloud_cmdb/cloud_providers/base_class/base_cmdb.py
threemystic_cloud_cmdb/cloud_providers/general/__init__.py
threemystic_cloud_cmdb/cloud_providers/general/cmdb_connector/auto_cmdb_connector.py
threemystic_cloud_cmdb/cloud_providers/general/cmdb_connector/ms365.py
threemystic_cloud_cmdb/cloud_providers/general/cmdb_connector/base_class/base.py
threemystic_cloud_cmdb/cloud_providers/general/config/step_1.py
threemystic_cloud_cmdb/cloud_providers/general/config/step_2.py
threemystic_cloud_cmdb/cloud_providers/general/config/step_2_cloud_share.py
threemystic_cmdb-0.1.10.dist-info/METADATA
threemystic_cmdb-0.1.10.dist-info/WHEEL
threemystic_cmdb-0.1.10.dist-info/entry_points.txt
threemystic_cmdb-0.1.10.dist-info/licenses/LICENSE
threemystic_cmdb-0.1.10.dist-info/RECORD
