Metadata-Version: 2.1
Name: threemystic-cmdb
Version: 0.1.10
Summary: A lightweight CMDB to help you track your cloud resources from various providers
Project-URL: Homepage, https://github.com/3MysticApes/3mystic_cloud_cmdb
Project-URL: Bug Tracker, https://github.com/3MysticApes/3mystic_cloud_cmdb/issues
Author: Ron Truex
License-Expression: MIT
License-File: LICENSE
Classifier: License :: OSI Approved :: MIT License
Classifier: Natural Language :: English
Classifier: Operating System :: OS Independent
Classifier: Programming Language :: Python :: 3.8
Classifier: Programming Language :: Python :: 3.9
Classifier: Programming Language :: Python :: 3.10
Classifier: Programming Language :: Python :: 3.11
Classifier: Programming Language :: Python :: Implementation :: CPython
Classifier: Programming Language :: Python :: Implementation :: PyPy
Requires-Python: >=3.8
Requires-Dist: asyncio>=3.4.3
Requires-Dist: colorama; platform_system == 'Windows'
Requires-Dist: lxml>=4.9.2
Requires-Dist: msgraph-sdk>=1.0.0a12
Requires-Dist: openpyxl>=3.1.2
Requires-Dist: polling2>=0.5.0
Requires-Dist: threemystic-cloud-data-client>=0.1.10
Requires-Dist: threemystic-common>=0.1.10
Requires-Dist: tqdm>=4.65.0
Requires-Dist: typing-extensions>=4.4.0
